file_op/__init__.py
file_op/find_delimiter.py
file_op-0.0.1.dist-info/LICENSE.txt
file_op-0.0.1.dist-info/METADATA
file_op-0.0.1.dist-info/WHEEL
file_op-0.0.1.dist-info/top_level.txt
file_op-0.0.1.dist-info/RECORD
