Metadata-Version: 2.1
Name: file-op
Version: 0.0.1
Summary: Find delimiter for a input file data
Home-page: https://github.com/pypa/sampleproject
Author: Arun Jaiswal
Author-email: arrrsh@gmail.com
License: UNKNOWN
Platform: UNKNOWN
Classifier: Programming Language :: Python :: 3
Classifier: License :: OSI Approved :: MIT License
Classifier: Operating System :: OS Independent
Classifier: Natural Language :: English
Requires-Python: >=3.6
